research_toolbox/__init__.py
research_toolbox/tb_augmentation.py
research_toolbox/tb_counting.py
research_toolbox/tb_data.py
research_toolbox/tb_debugging.py
research_toolbox/tb_environment.py
research_toolbox/tb_experiments.py
research_toolbox/tb_filesystem.py
research_toolbox/tb_gpus.py
research_toolbox/tb_interact.py
research_toolbox/tb_io.py
research_toolbox/tb_keras.py
research_toolbox/tb_logging.py
research_toolbox/tb_plotting.py
research_toolbox/tb_preprocessing.py
research_toolbox/tb_project.py
research_toolbox/tb_random.py
research_toolbox/tb_remote.py
research_toolbox/tb_resources.py
research_toolbox/tb_training.py
research_toolbox/tb_utils.py
research_toolbox-0.1.dist-info/LICENSE
research_toolbox-0.1.dist-info/METADATA
research_toolbox-0.1.dist-info/WHEEL
research_toolbox-0.1.dist-info/top_level.txt
research_toolbox-0.1.dist-info/RECORD
