Metadata-Version: 2.1
Name: research-toolbox
Version: 0.1
Summary: Utilities for reading and writing files, logging, and more.
Home-page: http://github.com/negrinho/research_toolbox
Author: Renato Negrinho
Author-email: renato.negrinho@gmail.com
License: MIT
Platform: UNKNOWN
Classifier: Intended Audience :: Science/Research
Classifier: Development Status :: 3 - Alpha
Classifier: License :: OSI Approved :: MIT License
Classifier: Programming Language :: Python :: 3.6
Classifier: Topic :: Scientific/Engineering :: Artificial Intelligence
Requires-Python: >=3.6
Requires-Dist: paramiko
Requires-Dist: numpy
Requires-Dist: scipy
Requires-Dist: psutil
